{
  "carvers": {},
  "downfall": 0.5,
  "effects": {
    "fog_color": 0,
    "sky_color": 0,
    "foliage_color": 8960833,
    "grass_color": 9419352,
    "mood_sound": {
      "block_search_extent": 8,
      "offset": 2.0,
      "sound": "minecraft:ambient.cave",
      "tick_delay": 6000
    },
    "water_color": 3902136,
    "water_fog_color": 2388383
  },
  "features": [
    [],
    [],
    [],
    [],
    [],
    [],
    [],
    [],
    [],
    [],
    ["minecraft:end_platform"]
  ],
  "has_precipitation": false,
  "spawn_costs": {},
  "spawners": {
    "ambient": [],
    "axolotls": [],
    "creature": [],
    "misc": [],
    "monster": [],
    "underground_water_creature": [],
    "water_ambient": [],
    "water_creature": []
  },
  "temperature": 0.5
}
